gazon/__init__.py
gazon/parser.py
gazon-1.0.0.dist-info/METADATA
gazon-1.0.0.dist-info/WHEEL
gazon-1.0.0.dist-info/top_level.txt
gazon-1.0.0.dist-info/RECORD
