Metadata-Version: 2.4
Name: gazon
Version: 1.0.0
Summary: Парсер информации о товарах с Ozon
Home-page: https://github.com/unionium/gazon
Author: RagnarekUA
Author-email: mrleyyt@gmail.com
Classifier: Programming Language :: Python :: 3
Classifier: License :: OSI Approved :: MIT License
Classifier: Operating System :: OS Independent
Requires-Python: >=3.7
Requires-Dist: selenium>=4.0
Requires-Dist: webdriver-manager>=3.0
Dynamic: author
Dynamic: author-email
Dynamic: classifier
Dynamic: description
Dynamic: description-content-type
Dynamic: home-page
Dynamic: requires-dist
Dynamic: requires-python
Dynamic: summary
